eve/__init__.py
eve/cli.py
eve/config.py
eve/commands/__init__.py
eve/commands/cmd_cal.py
eve/commands/cmd_col.py
eve/commands/cmd_pwd.py
eve/commands/cmd_search.py
eve/commands/cmd_tidy.py
eve/commands/cmd_weather.py
eve/commands/cmd_wifi-passwords.py
eve/service/__init__.py
eve/service/svc_weather.py
EVE_CLI_ASSISTANT-0.1.dist-info/LICENSE
EVE_CLI_ASSISTANT-0.1.dist-info/METADATA
EVE_CLI_ASSISTANT-0.1.dist-info/WHEEL
EVE_CLI_ASSISTANT-0.1.dist-info/entry_points.txt
EVE_CLI_ASSISTANT-0.1.dist-info/top_level.txt
EVE_CLI_ASSISTANT-0.1.dist-info/RECORD
